anygen/__init__.py
anygen/anygen.py
tests/__init__.py
tests/test_anygen.py
anygen-1.0.4.dist-info/LICENSE
anygen-1.0.4.dist-info/METADATA
anygen-1.0.4.dist-info/WHEEL
anygen-1.0.4.dist-info/top_level.txt
anygen-1.0.4.dist-info/RECORD
