Metadata-Version: 2.2
Name: anygen
Version: 1.0.4
Summary: A unified interface for text generation using Hugging Face, OpenAI, and Gemini models.
Home-page: https://github.com/macabdul9/AnyGen
Author: Abdul Waheed
Author-email: abdulwaheed1513@gmail.com
Classifier: Programming Language :: Python :: 3
Classifier: License :: OSI Approved :: MIT License
Classifier: Operating System :: OS Independent
Requires-Python: >=3.7
License-File: LICENSE
Requires-Dist: transformers
Requires-Dist: google-generativeai
Requires-Dist: requests
Requires-Dist: openai
Dynamic: author
Dynamic: author-email
Dynamic: classifier
Dynamic: description
Dynamic: description-content-type
Dynamic: home-page
Dynamic: requires-dist
Dynamic: requires-python
Dynamic: summary
